digitalocean/Account.py
digitalocean/Action.py
digitalocean/Balance.py
digitalocean/Certificate.py
digitalocean/Domain.py
digitalocean/Droplet.py
digitalocean/Firewall.py
digitalocean/FloatingIP.py
digitalocean/Image.py
digitalocean/Kernel.py
digitalocean/LoadBalancer.py
digitalocean/Manager.py
digitalocean/Metadata.py
digitalocean/Project.py
digitalocean/Record.py
digitalocean/Region.py
digitalocean/SSHKey.py
digitalocean/Size.py
digitalocean/Snapshot.py
digitalocean/Tag.py
digitalocean/VPC.py
digitalocean/Volume.py
digitalocean/__init__.py
digitalocean/baseapi.py
python_digitalocean-1.16.0.dist-info/LICENSE.txt
python_digitalocean-1.16.0.dist-info/METADATA
python_digitalocean-1.16.0.dist-info/WHEEL
python_digitalocean-1.16.0.dist-info/top_level.txt
python_digitalocean-1.16.0.dist-info/RECORD
